{
  "data": [
    {
      "participant": {
        "brand": "Organização A",
        "name": "Cliente_13",
        "cnpjNumber": "66908203136061",
        "urlComplementaryList": "https://empresa13.com/complementarylist"
      },
      "name": "Cartão Master Rewards",
      "identification": {
        "product": {
          "type": "MAESTRO_MASTERCARD_MAESTRO",
          "typeAdditionalInfo": "Informações adicionais"
        },
        "creditCard": {
          "network": "MASTERCARD",
          "networkAdditionalInfo": "Informações adicionais"
        }
      },
      "rewardsProgram": {
        "hasRewardProgram": false,
        "rewardProgramInfo": "https://empresa13.com/rewards"
      },
      "fees": {
        "services": [
          {
            "name": "ANUIDADE_DIFERENCIADA",
            "code": "ANUIDADE_DIFERENCIADA",
            "chargingTriggerInfo": "Cobrança anual parcelada",
            "prices": [
              {
                "interval": "3_FAIXA",
                "value": "1818.00",
                "currency": "BRL",
                "customers": {
                  "rate": "0.103"
                }
              }
            ],
            "minimum": {
              "value": "168.00",
              "currency": "BRL"
            },
            "maximum": {
              "value": "8853.00",
              "currency": "BRL"
            }
          }
        ]
      },
      "interest": {
        "rates": [
          {
            "referentialRateIndexer": "OUTROS_INDEXADORES",
            "rate": "0.138",
            "applications": [
              {
                "interval": "3_FAIXA",
                "indexer": {
                  "rate": "0.4"
                },
                "customers": {
                  "rate": "0.142"
                }
              }
            ],
            "minimumRate": "0.755",
            "maximumRate": "0.462"
          }
        ],
        "instalmentRates": [
          {
            "referentialRateIndexer": "OUTROS_INDEXADORES",
            "rate": "0.164",
            "applications": [
              {
                "interval": "3_FAIXA",
                "indexer": {
                  "rate": "0.14"
                },
                "customers": {
                  "rate": "0.22"
                }
              }
            ],
            "minimumRate": "0.0191",
            "maximumRate": "0.130"
          }
        ],
        "otherCredits": [
          {
            "code": "PAGAMENTOS_CONTAS",
            "codeAdditionalInfo": "Informações adicionais"
          }
        ]
      },
      "requiredWarranties": [
        "NAO_EXIGE_GARANTIA"
      ],
      "termsConditions": {
        "minimumFeeRate": "0.35",
        "additionalInfo": "NA",
        "elegibilityCriteriaInfo": "https://empresa13.com/creditcards_elegibility_criteria",
        "closingProcessInfo": "https://empresa13.com/creditcards_closing_process"
      }
    }
  ],
  "links": {
    "self": "https://api.banco.com.br/open-banking/opendata-creditcards/v1/resource",
    "first": "https://api.banco.com.br/open-banking/opendata-creditcards/v1/resource",
    "prev": "https://api.banco.com.br/open-banking/opendata-creditcards/v1/resource",
    "next": "https://api.banco.com.br/open-banking/opendata-creditcards/v1/resource",
    "last": "https://api.banco.com.br/open-banking/opendata-creditcards/v1/resource"
  },
  "meta": {
    "totalRecords": 1,
    "totalPages": 1
  }
}